diffhydro/__init__.py
diffhydro/utils.py
diffhydro/io/__init__.py
diffhydro/modules/__init__.py
diffhydro/modules/interp/__init__.py
diffhydro/modules/interp/cat_interp.py
diffhydro/modules/interp/utils.py
diffhydro/modules/routing/__init__.py
diffhydro/modules/routing/lti_router.py
diffhydro/modules/routing/lti_router_fusion.py
diffhydro/modules/runoff/__init__.py
diffhydro/modules/runoff/lstm.py
diffhydro/modules/runoff/runoff.py
diffhydro/pipelines/__init__.py
diffhydro/pipelines/base.py
diffhydro/pipelines/routing.py
diffhydro/pipelines/routing_calibration.py
diffhydro/pipelines/routing_learning.py
diffhydro/pipelines/routing_runoff_learning.py
diffhydro/pipelines/runoff_routing.py
diffhydro/pipelines/utils.py
diffhydro/structs/__init__.py
diffhydro-0.1.0.dist-info/licenses/LICENSE
diffhydro-0.1.0.dist-info/METADATA
diffhydro-0.1.0.dist-info/WHEEL
diffhydro-0.1.0.dist-info/top_level.txt
diffhydro-0.1.0.dist-info/RECORD
