Metadata-Version: 2.4
Name: diffhydro
Version: 0.1.0
Summary: Differentiable hydrological pipelines built on DiffRoute and PyTorch
Author-email: Tristan Hascoet <tristan.hascoet@gmail.com>
License-Expression: MIT
Project-URL: Homepage, https://github.com/TristHas/DiffHydro
Project-URL: Repository, https://github.com/TristHas/DiffHydro
Requires-Python: >=3.8
License-File: LICENSE
Requires-Dist: diffroute>=0.1.0
Requires-Dist: torch>=2.0.0
Requires-Dist: pandas
Requires-Dist: numpy
Requires-Dist: tqdm
Provides-Extra: examples
Requires-Dist: requests; extra == "examples"
Requires-Dist: xarray; extra == "examples"
Requires-Dist: s3fs; extra == "examples"
Dynamic: license-file
